huaweicloudsdkcpcs/__init__.py
huaweicloudsdkcpcs/v1/__init__.py
huaweicloudsdkcpcs/v1/cpcs_async_client.py
huaweicloudsdkcpcs/v1/cpcs_client.py
huaweicloudsdkcpcs/v1/model/__init__.py
huaweicloudsdkcpcs/v1/model/access_key_info.py
huaweicloudsdkcpcs/v1/model/add_cluster_port_request.py
huaweicloudsdkcpcs/v1/model/add_cluster_port_response.py
huaweicloudsdkcpcs/v1/model/app_info.py
huaweicloudsdkcpcs/v1/model/app_resource_info.py
huaweicloudsdkcpcs/v1/model/associate_apps_request.py
huaweicloudsdkcpcs/v1/model/associate_apps_request_body.py
huaweicloudsdkcpcs/v1/model/associate_apps_response.py
huaweicloudsdkcpcs/v1/model/association_info.py
huaweicloudsdkcpcs/v1/model/auth_object.py
huaweicloudsdkcpcs/v1/model/auth_object_auth.py
huaweicloudsdkcpcs/v1/model/auth_object_auth_access_key.py
huaweicloudsdkcpcs/v1/model/auth_object_scope.py
huaweicloudsdkcpcs/v1/model/auth_object_scope_cluster.py
huaweicloudsdkcpcs/v1/model/authorize_access_keys_request.py
huaweicloudsdkcpcs/v1/model/authorize_access_keys_request_body.py
huaweicloudsdkcpcs/v1/model/authorize_access_keys_response.py
huaweicloudsdkcpcs/v1/model/batch_access_keys_request_body.py
huaweicloudsdkcpcs/v1/model/batch_disable_access_keys_request.py
huaweicloudsdkcpcs/v1/model/batch_disable_access_keys_response.py
huaweicloudsdkcpcs/v1/model/batch_enable_access_keys_request.py
huaweicloudsdkcpcs/v1/model/batch_enable_access_keys_response.py
huaweicloudsdkcpcs/v1/model/cancel_authorize_access_keys_request.py
huaweicloudsdkcpcs/v1/model/cancel_authorize_access_keys_response.py
huaweicloudsdkcpcs/v1/model/ccsp_cluster_info.py
huaweicloudsdkcpcs/v1/model/ccsp_instance_info.py
huaweicloudsdkcpcs/v1/model/ccsp_service_info.py
huaweicloudsdkcpcs/v1/model/check_cluster_port_request.py
huaweicloudsdkcpcs/v1/model/check_cluster_port_response.py
huaweicloudsdkcpcs/v1/model/cloud_service_info.py
huaweicloudsdkcpcs/v1/model/create_app_access_key_request.py
huaweicloudsdkcpcs/v1/model/create_app_access_key_request_body.py
huaweicloudsdkcpcs-3.1.184.dist-info/METADATA
huaweicloudsdkcpcs-3.1.184.dist-info/WHEEL
huaweicloudsdkcpcs-3.1.184.dist-info/licenses/LICENSE
huaweicloudsdkcpcs-3.1.184.dist-info/RECORD
